{
    "background": "#fafafa",
    "black": "#0a0a0a",
    "blue": "#2563eb",
    "brightBlack": "#262626",
    "brightBlue": "#1d4ed8",
    "brightCyan": "#0e7490",
    "brightGreen": "#15803d",
    "brightPurple": "#7e22ce",
    "brightRed": "#b91c1c",
    "brightWhite": "#fafafa",
    "brightYellow": "#a16207",
    "cursorColor": "#0a0a0a",
    "cyan": "#0891b2",
    "foreground": "#0a0a0a",
    "green": "#16a34a",
    "name": "Airfoil Light",
    "purple": "#9333ea",
    "red": "#dc2626",
    "selectionBackground": "#60a5fa",
    "white": "#e5e5e5",
    "yellow": "#ca8a04"
}